{
    "accumulateData": false,
    "accumulationFilePattern": "(?P<fileName>[\\w]*).sav",
    "checkFileSizes": true,
    "defaultCaptureOutputOutDir": "none",
    "defaultConfigDir": ".",
    "defaultInputDir": "D:/lib/SPSS-BatchProcessor/data/importFiles/in",
    "defaultOutDir": "D:/lib/SPSS-BatchProcessor/data/importFiles/out",
    "defaultSPSSDir": "D:/lib/SPSS-BatchProcessor/data/importFiles",
    "defaultSyntaxOutDir": "none",
    "inputFiles": [
        "D:/lib/SPSS-BatchProcessor/data/importFiles/in/data.csv"
    ],
    "inputRegexPattern": "(?P<fileName>[\\w]*).csv",
    "inputSearchPattern": ".csv",
    "outputDir": "D:/lib/SPSS-BatchProcessor/data/importFiles/out",
    "outputFilePattern": "<fileName>.sav",
    "placeholders": {
        "DUMMY": "DUMMY",
        "INFILE": "",
        "OUTPUTFILE": ""
    },
    "programVersion": 0.8,
    "simulateProcessing": false,
    "spssFile": "D:/lib/SPSS-BatchProcessor/data/importFiles/importFilesSPSS.sps"
}